CHANGELOG.md
LICENSE
README.md
jsun/__init__.py
jsun/__main__.py
jsun/decoder.py
jsun/encoder.py
jsun/exc.py
jsun/obj.py
jsun/scanner.py
jsun-1.0a1.dist-info/entry_points.txt
jsun-1.0a1.dist-info/LICENSE
jsun-1.0a1.dist-info/WHEEL
jsun-1.0a1.dist-info/METADATA
jsun-1.0a1.dist-info/RECORD
