Metadata-Version: 2.1
Name: jsun
Version: 1.0a1
Summary: JSON encoding & decoding with extra features
Home-page: https://github.com/wylee/jsun
License: MIT
Keywords: json
Author: Wyatt Baldwin
Author-email: self@wyattbaldwin.com
Requires-Python: >=3.7,<4.0
Classifier: License :: OSI Approved :: MIT License
Classifier: Programming Language :: Python :: 3
Classifier: Programming Language :: Python :: 3.10
Classifier: Programming Language :: Python :: 3.7
Classifier: Programming Language :: Python :: 3.8
Classifier: Programming Language :: Python :: 3.9
Requires-Dist: arrow (>=1.1.0,<2.0.0)
Project-URL: Repository, https://github.com/wylee/jsun
